llama_index/agent/openai_legacy/__init__.py
llama_index/agent/openai_legacy/context_retriever_agent.py
llama_index/agent/openai_legacy/openai_agent.py
llama_index/agent/openai_legacy/retriever_openai_agent.py
llama_index/agent/openai_legacy/utils.py
llama_index_agent_openai_legacy-0.3.4.dist-info/METADATA
llama_index_agent_openai_legacy-0.3.4.dist-info/WHEEL
llama_index_agent_openai_legacy-0.3.4.dist-info/licenses/LICENSE
llama_index_agent_openai_legacy-0.3.4.dist-info/RECORD
