Metadata-Version: 2.4
Name: llama-index-agent-openai-legacy
Version: 0.3.4
Summary: llama-index agent openai-legacy integration
Author-email: Your Name <you@example.com>
License-Expression: MIT
License-File: LICENSE
Requires-Python: <4.0,>=3.9
Requires-Dist: llama-index-core<0.13,>=0.12.41
Requires-Dist: llama-index-llms-openai<0.5,>=0.4.0
